{"info":{"_postman_id":"7a4b88d2-4a40-41b5-82c8-6083d05c00b5","name":"Restful Booker API Testing hint","schema":"https://schema.getpostman.com/json/collection/v2.1.0/collection.json"},"item":[{"name":"CRUD","item":[{"name":"Ping - HealthCheck","event":[{"listen":"test","script":{"id":"17215e07-43b0-4604-a5d6-635363725dc8","exec":["pm.test(\"Status code is 201\", function () {\r","    pm.response.to.have.status(201);\r","});\r","\r",""],"type":"text/javascript"}}],"id":"d5b14b1b-6128-4aa1-a80f-9eabcc71d315","protocolProfileBehavior":{"disableBodyPruning":true},"request":{"method":"GET","header":[],"url":{"raw":"https://{{url}}/ping","protocol":"https","host":["{{url}}"],"path":["ping"]}},"response":[]},{"name":"Booking - GetBookingIds","event":[{"listen":"test","script":{"type":"text/javascript","exec":["pm.test(\"Content-Type is present\", function () {\r","    pm.response.to.have.header(\"Content-Type\");\r","});\r","\r","pm.test(\"Response time is less than 5000ms\", function () {\r","    pm.expect(pm.response.responseTime).to.be.below(5000);\r","});"],"id":"d44310d4-180a-4b8e-8384-58eecfd59e86"}}],"id":"beda9d37-4175-4706-b86a-d3b9656a66fc","protocolProfileBehavior":{"disableBodyPruning":true},"request":{"auth":{"type":"digest","digest":[{"key":"algorithm","value":"MD5","type":"string"},{"key":"username","value":"zczx","type":"string"},{"key":"password","value":"czxcz","type":"string"}]},"method":"GET","header":[{"key":"x-api-key","value":"PRAMODDUTTA","type":"text"}],"url":{"raw":"https://{{url}}/booking","protocol":"https","host":["{{url}}"],"path":["booking"]}},"response":[]},{"name":"Booking - GetBooking Copy","id":"c1d7ef17-c323-41a7-9543-8467cd8d5777","protocolProfileBehavior":{"disableBodyPruning":true},"request":{"method":"GET","header":[],"url":{"raw":"https://restful-booker.herokuapp.com/booking/1859","protocol":"https","host":["restful-booker","herokuapp","com"],"path":["booking","1859"]}},"response":[]},{"name":"POST Create Booking","event":[{"listen":"test","script":{"type":"text/javascript","exec":["pm.test(\"Status code is 200\", function () {\r","    pm.response.to.have.status(200);\r","});"],"id":"2036e221-4e7e-45fb-8991-94d0e6ab307a"}}],"id":"401f906b-6b61-4038-b625-8b716604b468","protocolProfileBehavior":{"disableBodyPruning":true},"request":{"method":"POST","header":[{"key":"Content-Type","value":"application/json"}],"body":{"mode":"raw","raw":"{\n    \"firstname\" : \"{{$randomFirstName}}\",\n    \"lastname\" : \"Dutta\",\n    \"totalprice\" : {{$randomInt}},\n    \"depositpaid\" : false,\n    \"bookingdates\" : {\n        \"checkin\" : \"{{$randomDateRecent}}\",\n        \"checkout\" : \"2022-01-01\"\n    },\n    \"additionalneeds\" : \"Lunch\"\n}","options":{"raw":{"language":"json"}}},"url":{"raw":"https://restful-booker.herokuapp.com/booking","protocol":"https","host":["restful-booker","herokuapp","com"],"path":["booking"]}},"response":[]},{"name":"Update with No Auth","event":[{"listen":"test","script":{"type":"text/javascript","exec":["pm.test(\"No Entry without Auth,Status code is 403 Forbidden\", function () {\r","    pm.response.to.have.status(403);\r","});"],"id":"eb8b6ce8-1290-4286-9daf-cd62dbc68906"}}],"id":"a0ccd790-b34b-4aef-9d28-fd8c24bcaef0","protocolProfileBehavior":{"disableBodyPruning":true},"request":{"method":"PUT","header":[{"key":"Content-Type","value":"application/json"},{"key":"Accept","value":"application/json"},{"key":"Cookie","value":"token=6d1f5c03348f5af","disabled":true}],"body":{"mode":"raw","raw":"{\n    \"firstname\" : \"James\",\n    \"lastname\" : \"Brown\",\n    \"totalprice\" : 111,\n    \"depositpaid\" : true,\n    \"bookingdates\" : {\n        \"checkin\" : \"2018-01-01\",\n        \"checkout\" : \"2019-01-01\"\n    },\n    \"additionalneeds\" : \"Breakfast\"\n}"},"url":{"raw":"https://restful-booker.herokuapp.com/booking/3050","protocol":"https","host":["restful-booker","herokuapp","com"],"path":["booking","3050"]}},"response":[]},{"name":"Create Auth","event":[{"listen":"test","script":{"id":"ff779370-3fed-4016-a031-96c95df94a4d","exec":["pm.test(\"Check Token is not null\",function(){","    pm.expect(pm.response.json()[\"Token\"]).not.to.be.null;","});"],"type":"text/javascript"}}],"id":"615f3b5b-0796-4007-8ef1-58892c353c6e","protocolProfileBehavior":{"disableBodyPruning":true},"request":{"method":"POST","header":[],"body":{"mode":"raw","raw":"{\r\n    \"username\" : \"admin\",\r\n    \"password\" : \"password123\"\r\n}","options":{"raw":{"language":"json"}}},"url":{"raw":"https://restful-booker.herokuapp.com/auth","protocol":"https","host":["restful-booker","herokuapp","com"],"path":["auth"]}},"response":[]},{"name":"Booking - UpdateBooking Basic Auth","id":"3b665d08-1a18-488e-b649-e5bab47a98d5","protocolProfileBehavior":{"disableBodyPruning":true},"request":{"method":"PUT","header":[{"key":"Cookie","value":"token=163b94733cbfca7","type":"text"}],"body":{"mode":"raw","raw":"{\r\n    \"firstname\" : \"James\",\r\n    \"lastname\" : \"Brown\",\r\n    \"totalprice\" : 111,\r\n    \"depositpaid\" : true,\r\n    \"bookingdates\" : {\r\n        \"checkin\" : \"2018-01-01\",\r\n        \"checkout\" : \"2019-01-01\"\r\n    },\r\n    \"additionalneeds\" : \"Breakfast\"\r\n}","options":{"raw":{"language":"json"}}},"url":{"raw":"https://restful-booker.herokuapp.com/booking/10972","protocol":"https","host":["restful-booker","herokuapp","com"],"path":["booking","10972"]}},"response":[]},{"name":"Update Booking with Cookie","id":"d5b08c1a-9979-46e1-836f-780b320cc07e","protocolProfileBehavior":{"disableBodyPruning":true},"request":{"method":"PUT","header":[{"key":"Content-Type","value":"application/json"},{"key":"Accept","value":"application/json"},{"key":"Cookie","value":"token=6d1f5c03348f5af"}],"body":{"mode":"raw","raw":"{\n    \"firstname\" : \"James\",\n    \"lastname\" : \"Brown\",\n    \"totalprice\" : 111,\n    \"depositpaid\" : true,\n    \"bookingdates\" : {\n        \"checkin\" : \"2018-01-01\",\n        \"checkout\" : \"2019-01-01\"\n    },\n    \"additionalneeds\" : \"Breakfast\"\n}"},"url":{"raw":"https://restful-booker.herokuapp.com/booking/3050","protocol":"https","host":["restful-booker","herokuapp","com"],"path":["booking","3050"]}},"response":[]},{"name":"Booking - PartialUpdateBooking","id":"1bd0b43b-7bce-438a-99eb-d64fca39d9b0","protocolProfileBehavior":{"disableBodyPruning":true},"request":{"method":"PATCH","header":[{"key":"Cookie","value":"token=6d1f5c03348f5af","type":"text"}],"body":{"mode":"raw","raw":"{\r\n    \"firstname\" : \"Pramod\"\r\n}","options":{"raw":{"language":"json"}}},"url":{"raw":"https://restful-booker.herokuapp.com/booking/3050","protocol":"https","host":["restful-booker","herokuapp","com"],"path":["booking","3050"]}},"response":[]},{"name":"Delete Booking","id":"0d24956b-e1cc-4c52-9a64-4ebc1e92c0f6","protocolProfileBehavior":{"disableBodyPruning":true},"request":{"method":"PATCH","header":[{"key":"Cookie","value":"token=6d1f5c03348f5af","type":"text"}],"body":{"mode":"raw","raw":"{\r\n    \"firstname\" : \"Pramod\"\r\n}","options":{"raw":{"language":"json"}}},"url":{"raw":"https://restful-booker.herokuapp.com/booking/3050","protocol":"https","host":["restful-booker","herokuapp","com"],"path":["booking","3050"]}},"response":[]},{"name":"Delete Booking","id":"475ea192-cc40-430c-afca-7f087adaa0ad","protocolProfileBehavior":{"disableBodyPruning":true},"request":{"auth":{"type":"basic","basic":[{"key":"password","value":"password123","type":"string"},{"key":"username","value":"admin","type":"string"},{"key":"showPassword","value":false,"type":"boolean"}]},"method":"DELETE","header":[{"key":"Cookie","value":"token=163b94733cbfca7","type":"text"}],"url":{"raw":"https://restful-booker.herokuapp.com/booking/8613","protocol":"https","host":["restful-booker","herokuapp","com"],"path":["booking","8613"]}},"response":[]}],"id":"b0b5fc4c-0b7d-49ce-95af-b1e0d67ef4bf"},{"name":"Assignment 1  - Task 1","item":[{"name":"A1T1- Step 1 - Create Booking","event":[{"listen":"test","script":{"id":"11313701-95f7-4cb5-8c1b-ae375b63c903","exec":["pm.test(\"Status code is 200\", function () {\r","    pm.environment.set(\"e_bookingid\",pm.response.json()[\"bookingid\"]);\r","    pm.response.to.have.status(200);\r","});"],"type":"text/javascript"}}],"id":"0b35928d-ef4f-4380-9228-05185905294c","protocolProfileBehavior":{"disableBodyPruning":true},"request":{"method":"POST","header":[{"key":"Content-Type","value":"application/json"}],"body":{"mode":"raw","raw":"{\n    \"firstname\" : \"{{$randomFirstName}}\",\n    \"lastname\" : \"Dutta\",\n    \"totalprice\" : {{$randomInt}},\n    \"depositpaid\" : false,\n    \"bookingdates\" : {\n        \"checkin\" : \"{{$randomDateRecent}}\",\n        \"checkout\" : \"2022-01-01\"\n    },\n    \"additionalneeds\" : \"Lunch\"\n}","options":{"raw":{"language":"json"}}},"url":{"raw":"https://restful-booker.herokuapp.com/booking","protocol":"https","host":["restful-booker","herokuapp","com"],"path":["booking"]}},"response":[]},{"name":"A1T1 - Step 2 UpdateBooking","event":[{"listen":"test","script":{"id":"9cb1c61f-e6ee-4dad-b718-1b8835179cac","exec":["pm.test(\"Your test name\", function () {","    var jsonData = pm.response.json();","    pm.expect(jsonData[\"firstname\"]).to.eql(\"James\");","});"],"type":"text/javascript"}}],"id":"fd42c178-89ff-4559-8446-c576a1e53613","protocolProfileBehavior":{"disableBodyPruning":true},"request":{"auth":{"type":"basic","basic":[{"key":"password","value":"password123","type":"string"},{"key":"username","value":"admin","type":"string"},{"key":"showPassword","value":false,"type":"boolean"}]},"method":"PUT","header":[{"key":"Cookie","value":"token=163b94733cbfca7","type":"text"}],"body":{"mode":"raw","raw":"{\r\n    \"firstname\" : \"James\",\r\n    \"lastname\" : \"Brown\",\r\n    \"totalprice\" : 111,\r\n    \"depositpaid\" : true,\r\n    \"bookingdates\" : {\r\n        \"checkin\" : \"2018-01-01\",\r\n        \"checkout\" : \"2019-01-01\"\r\n    },\r\n    \"additionalneeds\" : \"Breakfast\"\r\n}","options":{"raw":{"language":"json"}}},"url":{"raw":"https://restful-booker.herokuapp.com/booking/{{e_bookingid}}","protocol":"https","host":["restful-booker","herokuapp","com"],"path":["booking","{{e_bookingid}}"]}},"response":[]},{"name":"A1T1 Step 3 - GetBooking","event":[{"listen":"test","script":{"id":"adad407c-676c-48e8-b6a9-f5b81267290e","exec":["pm.test(\"Get verified the firstName\", function () {","    var jsonData = pm.response.json();","    pm.expect(jsonData[\"firstname\"]).to.eql(\"James\");","});"],"type":"text/javascript"}}],"id":"bf9049ea-70cc-4b17-a1b5-dd6295fbcb25","protocolProfileBehavior":{"disableBodyPruning":true},"request":{"method":"GET","header":[],"url":{"raw":"https://restful-booker.herokuapp.com/booking/{{e_bookingid}}","protocol":"https","host":["restful-booker","herokuapp","com"],"path":["booking","{{e_bookingid}}"]}},"response":[]}],"id":"da2e970d-8978-4220-8ed8-9fb027bbf425"},{"name":"Assignment 1  - Task 2","item":[],"id":"fac8288d-8ac5-470e-91ef-d5c1d29cb994"},{"name":"Assignment 1  - Task 3","item":[],"id":"b370bf6c-d8c7-4800-bd42-63492edfce8b"},{"name":"Assignment 1  - Task 4","item":[],"id":"c4899596-7eff-4d1d-b120-7a5834c0b80f"},{"name":"Assignment 1  - Task 5","item":[{"name":"A1T1- Step 1 - Create Booking (Wrong Payload)","event":[{"listen":"test","script":{"id":"e19b7f62-a923-4841-b348-6343a1d638f9","exec":["pm.test(\"Status code is 500\", function () {\r","    pm.response.to.have.status(500);\r","});"],"type":"text/javascript"}}],"id":"e2b33cc6-7d38-4301-a6c2-4ca4accd1fdd","protocolProfileBehavior":{"disableBodyPruning":true},"request":{"method":"POST","header":[{"key":"Content-Type","value":"application/json","disabled":true}],"body":{"mode":"raw","raw":"{\n    \"firstname\" : \"{{$randomFirstName}}\",\n    \"lastname\" : \"Dutta\",\n    \"totalprice\" : {{$randomInt}},\n    \"depositpaid\" : false,\n    \"bookingdates\" : {\n        \"checkin\" : \"{{$randomDateRecent}}\",\n        \"checkout\" : \"2022-01-01\"\n    },\n    \"additionalneeds\" : \"Lunch\"\n}","options":{"raw":{"language":"text"}}},"url":{"raw":"https://restful-booker.herokuapp.com/booking","protocol":"https","host":["restful-booker","herokuapp","com"],"path":["booking"]}},"response":[]}],"id":"04abcb31-cc90-4dcc-ac51-bbe20ab4655e"}],"event":[{"listen":"prerequest","script":{"id":"bf6d5d20-74b9-4a17-982d-78e7a4a0f234","type":"text/javascript","exec":[""]}},{"listen":"test","script":{"id":"a2976c90-edc7-4a47-a2ce-a5642a5b4a30","type":"text/javascript","exec":[""]}}],"variable":[{"id":"713340bb-afdc-4d8e-8f72-3c638d12438e","key":"url","value":"collection.com","type":"string"}]}